trayan/__init__.py
trayan/base.py
trayan/quick.py
trayan/aio/__init__.py
trayan/aio/quick.py
trayan/aio/translator.py
trayan/models/__init__.py
trayan/models/errors/__init__.py
trayan/models/errors/parse.py
trayan/models/errors/request.py
trayan/models/request/__init__.py
trayan/models/request/method.py
trayan/models/translator/__init__.py
trayan/models/translator/api.py
trayan/models/translator/language.py
trayan/sync/__init__.py
trayan/sync/quick.py
trayan/sync/translator.py
trayan/utils/__init__.py
trayan/utils/cache.py
trayan-0.1.5.dist-info/LICENSE
trayan-0.1.5.dist-info/METADATA
trayan-0.1.5.dist-info/WHEEL
trayan-0.1.5.dist-info/top_level.txt
trayan-0.1.5.dist-info/RECORD
