Metadata-Version: 2.1
Name: trayan
Version: 0.1.5
Home-page: https://github.com/re1von-project/trayan
Author: re1von project
Author-email: re1von_project@bk.ru
License-File: LICENSE
